pitchr/__init__.py
pitchr/df_import.py
pitchr/harmony_maker.py
pitchr/helper.py
pitchr/lyexport.py
pitchr/model_maker.py
pitchr/music.py
pitchr/pitch_tagger.py
pitchr/playing.py
pitchr/predict.py
pitchr/utils.py
pitchr/xml_parser.py
tests/__init__.py
tests/test_accidentals.py
tests/test_chord.py
tests/test_clef.py
tests/test_df_import.py
tests/test_exporting.py
tests/test_harmony_maker.py
tests/test_key.py
tests/test_measure.py
tests/test_model.py
tests/test_music.py
tests/test_note.py
tests/test_part.py
tests/test_pitch.py
tests/test_playing.py
tests/test_predictability.py
tests/test_rest.py
tests/test_score.py
tests/test_staff.py
tests/test_time.py
pitchr-1.1.0.dist-info/LICENSE
pitchr-1.1.0.dist-info/METADATA
pitchr-1.1.0.dist-info/WHEEL
pitchr-1.1.0.dist-info/top_level.txt
pitchr-1.1.0.dist-info/RECORD
