Metadata-Version: 2.1
Name: pitchr
Version: 1.1.0
Summary: A Python library and framework for composing and playing music.
Home-page: https://github.com/thedpws/pitcher
Author: Vinicius Martinson, Brian McDowell, Jacob Menke, Aeyzechiah Vasquez, Caleb Wong
Author-email: azvasquez99@gmail.com
License: UNKNOWN
Platform: UNKNOWN
Classifier: Programming Language :: Python :: 3
Classifier: License :: OSI Approved :: GNU General Public License (GPL)
Classifier: Operating System :: OS Independent
Requires-Python: >=3.6
Requires-Dist: absl-py (==0.9.0)
Requires-Dist: astunparse (==1.6.3)
Requires-Dist: beautifulsoup4 (==4.9.1)
Requires-Dist: bs4 (==0.0.1)
Requires-Dist: cachetools (==4.1.1)
Requires-Dist: certifi (==2020.6.20)
Requires-Dist: chardet (==3.0.4)
Requires-Dist: cycler (==0.10.0)
Requires-Dist: gast (==0.3.3)
Requires-Dist: google-auth (==1.20.0)
Requires-Dist: google-auth-oauthlib (==0.4.1)
Requires-Dist: google-pasta (==0.2.0)
Requires-Dist: grpcio (==1.30.0)
Requires-Dist: h5py (==2.10.0)
Requires-Dist: idna (==2.10)
Requires-Dist: Keras-Preprocessing (==1.1.2)
Requires-Dist: kiwisolver (==1.2.0)
Requires-Dist: lxml (==4.5.2)
Requires-Dist: Markdown (==3.2.2)
Requires-Dist: matplotlib (==3.2.2)
Requires-Dist: mido (==1.2.9)
Requires-Dist: mingus (==0.6.0)
Requires-Dist: numpy (==1.18.5)
Requires-Dist: oauthlib (==3.1.0)
Requires-Dist: opt-einsum (==3.3.0)
Requires-Dist: pandas (==1.0.5)
Requires-Dist: Pillow (==7.1.2)
Requires-Dist: protobuf (==3.12.4)
Requires-Dist: pyasn1 (==0.4.8)
Requires-Dist: pyasn1-modules (==0.2.8)
Requires-Dist: pyparsing (==2.4.7)
Requires-Dist: python-dateutil (==2.8.1)
Requires-Dist: pytz (==2020.1)
Requires-Dist: requests (==2.24.0)
Requires-Dist: requests-oauthlib (==1.3.0)
Requires-Dist: rsa (==4.6)
Requires-Dist: scipy (==1.4.1)
Requires-Dist: simpleaudio (==1.0.4)
Requires-Dist: six (==1.15.0)
Requires-Dist: soupsieve (==2.0.1)
Requires-Dist: tensorboard (==2.3.0)
Requires-Dist: tensorboard-plugin-wit (==1.7.0)
Requires-Dist: tensorflow (==2.3.0)
Requires-Dist: tensorflow-estimator (==2.3.0)
Requires-Dist: termcolor (==1.1.0)
Requires-Dist: timidity (==0.1.2)
Requires-Dist: urllib3 (==1.25.10)
Requires-Dist: Werkzeug (==1.0.1)
Requires-Dist: wrapt (==1.12.1)
